anitya_telegram/anitya_tg_gw.py
anitya_telegram-0.0.5.dist-info/METADATA
anitya_telegram-0.0.5.dist-info/WHEEL
anitya_telegram-0.0.5.dist-info/top_level.txt
anitya_telegram-0.0.5.dist-info/RECORD
