Metadata-Version: 2.1
Name: anitya-telegram
Version: 0.0.5
Summary: Telegram gateway for Anitya release monitoring system
Author-email: mirko <mirko+anitya@smthd.com>
Project-URL: Homepage, https://gitea.smthd.com/mirko/anitya-telegram
Classifier: Programming Language :: Python :: 3
Classifier: License :: OSI Approved :: GNU General Public License v2 or later (GPLv2+)
Classifier: Operating System :: POSIX :: Linux
Requires-Python: >=3.8
Requires-Dist: fedora-messaging ==3.6.*
Requires-Dist: anitya-schema ==2.2.*
Requires-Dist: python-telegram-bot-raw ==21.3
